llama_agentic_system/__init__.py
llama_agentic_system/agentic_system.py
llama_agentic_system/api_instance.py
llama_agentic_system/client.py
llama_agentic_system/event_logger.py
llama_agentic_system/server.py
llama_agentic_system/system_prompt.py
llama_agentic_system/utils.py
llama_agentic_system/api/__init__.py
llama_agentic_system/api/config.py
llama_agentic_system/api/datatypes.py
llama_agentic_system/api/endpoints.py
llama_agentic_system/cli/__init__.py
llama_agentic_system/cli/subcommand_modules.py
llama_agentic_system/cli/agentic_system/__init__.py
llama_agentic_system/cli/agentic_system/command.py
llama_agentic_system/cli/agentic_system/configure.py
llama_agentic_system/data/default.yaml
llama_agentic_system/tools/__init__.py
llama_agentic_system/tools/base.py
llama_agentic_system/tools/builtin.py
llama_agentic_system/tools/custom.py
llama_agentic_system/tools/safety.py
llama_agentic_system/tools/ipython_tool/__init__.py
llama_agentic_system/tools/ipython_tool/code_env_prefix.py
llama_agentic_system/tools/ipython_tool/code_execution.py
llama_agentic_system/tools/ipython_tool/matplotlib_custom_backend.py
llama_agentic_system/tools/ipython_tool/utils.py
llama_agentic_system-0.0.2.dist-info/LICENSE
llama_agentic_system-0.0.2.dist-info/METADATA
llama_agentic_system-0.0.2.dist-info/WHEEL
llama_agentic_system-0.0.2.dist-info/top_level.txt
llama_agentic_system-0.0.2.dist-info/RECORD
